{"cameraMode":{"drawMode":0,"name":"Shaded","section":"Shading Mode"},"sceneLighting":false,"audioPlay":false,"sceneViewState":{"m_AlwaysRefresh":false,"showFog":true,"showSkybox":false,"showFlares":true,"showImageEffects":true,"showParticleSystems":true,"showVisualEffectGraphs":true,"m_FxEnabled":true},"in2DMode":false,"pivot":{"x":12.70867919921875,"y":0.3379698395729065,"z":25.084484100341798},"rotation":{"x":0.31381332874298098,"y":-0.08218108117580414,"z":0.0273846797645092,"w":0.9457226395606995},"size":3.583456516265869,"orthographic":false}